hipims_io/Boundary.py
hipims_io/InputHipims.py
hipims_io/Landcover.py
hipims_io/OutputHipims.py
hipims_io/Rainfall.py
hipims_io/Raster.py
hipims_io/Summary.py
hipims_io/__init__.py
hipims_io/demo_functions.py
hipims_io/grid_show.py
hipims_io/indep_functions.py
hipims_io/rainfall_processing.py
hipims_io/spatial_analysis.py
hipims_io/sample/DEM.gz
hipims_io/sample/landcover.gz
hipims_io/sample/rain_mask.gz
hipims_io/sample/rain_source.csv
hipims_io-0.6.3.dist-info/LICENSE.txt
hipims_io-0.6.3.dist-info/METADATA
hipims_io-0.6.3.dist-info/WHEEL
hipims_io-0.6.3.dist-info/top_level.txt
hipims_io-0.6.3.dist-info/RECORD
