Metadata-Version: 2.1
Name: hipims-io
Version: 0.6.3
Summary: To process input and output files of the HiPIMS model
Home-page: https://github.com/mingxiaodong/hipims_io_python
Author: Xiaodong Ming
Author-email: x.ming@lboro.ac.uk
License: LICENSE.txt
Keywords: HiPIMS model IO
Platform: UNKNOWN
Classifier: Development Status :: 3 - Alpha
Classifier: Programming Language :: Python :: 3
Classifier: License :: OSI Approved :: MIT License
Classifier: Programming Language :: Python :: 3
Classifier: Operating System :: OS Independent
Requires-Python: >=3.6
Requires-Dist: rasterio
Requires-Dist: scipy
Requires-Dist: pyshp
Requires-Dist: fiona
Requires-Dist: hydro-raster
Requires-Dist: matplotlib
Requires-Dist: numpy
Requires-Dist: pandas
Requires-Dist: imageio
